README.rst
setup.cfg
setup.py
amber_runner/MD.py
amber_runner/__init__.py
amber_runner/command.py
amber_runner/executables.py
amber_runner/inputs.py
amber_runner.egg-info/PKG-INFO
amber_runner.egg-info/SOURCES.txt
amber_runner.egg-info/dependency_links.txt
amber_runner.egg-info/requires.txt
amber_runner.egg-info/top_level.txt