Metadata-Version: 1.2
Name: amber-runner
Version: 0.0.0
Summary: Batch execution for Amber MD
Home-page: https://github.com/sizmailov/amber-runner
Maintainer: Sergei Izmailov
Maintainer-email: sergei.a.izmailov@gmail.com
License: BSD
Platform: UNKNOWN
